yft/__init__.py
yft/corp_readers.py
yft/lexstats.py
yft/string.py
yft-0.1.1.dist-info/METADATA
yft-0.1.1.dist-info/WHEEL
yft-0.1.1.dist-info/top_level.txt
yft-0.1.1.dist-info/RECORD
