Metadata-Version: 2.1
Name: yft
Version: 0.1.1
Summary: Utility functions for text processing
Home-page: http://github.com/liao961120/yft
Author: Yongfu Liao
Author-email: liao961120@github.com
License: MIT
Platform: UNKNOWN
Requires-Dist: tqdm
Requires-Dist: networkx
